MANIFEST.in
README.md
requirements.txt
setup.py
version.py
officepy/__init__.py
officepy/auth.py
officepy/customfunctionmanager.py
officepy/customfunctions.py
officepy/excel.py
officepy/exceldemolib.py
officepy/httphelper.py
officepy/mylib.py
officepy/runtime.py
officepy/test.py
officepy/test_cfdecorate.py
officepy.egg-info/PKG-INFO
officepy.egg-info/SOURCES.txt
officepy.egg-info/dependency_links.txt
officepy.egg-info/requires.txt
officepy.egg-info/top_level.txt
officepy/nbextension/officepy.json
officepy/nbextension/static/extension.js
officepy/nbserver_extension/__init__.py
officepy/nbserver_extension/officepy.json
officepy/nbserver_extension/server_extension.py