Metadata-Version: 2.1
Name: officepy
Version: 0.0.4
Summary: Office Python API
Home-page: https://github.com/officedev
Author: Office Dev
Author-email: officepy@microsoft.com
License: UNKNOWN
Platform: UNKNOWN
Requires-Python: >=3.6.3
